DMDO/DA.py
DMDO/DMDO.py
DMDO/MDA.py
DMDO/MDO.py
DMDO/SP.py
DMDO/__init__.py
DMDO/_common.py
DMDO/_globals.py
DMDO/_protocols.py
DMDO/coordinator.py
DMDO/preprocess.py
DMDO/variables.py
DMDO-2404.dist-info/LICENSE
DMDO-2404.dist-info/METADATA
DMDO-2404.dist-info/WHEEL
DMDO-2404.dist-info/top_level.txt
DMDO-2404.dist-info/RECORD
