Metadata-Version: 2.1
Name: DMDO
Version: 2404
Summary: Distributed Multidisciplinary Design Optimization (DMDO)
Home-page: https://github.com/Ahmed-Bayoumy/DMDO
Author: Ahmed H. Bayoumy
Author-email: ahmed.bayoumy@mail.mcgill.ca
Project-URL: Bug Tracker, https://github.com/Ahmed-Bayoumy/DMDO/issues
Classifier: Programming Language :: Python :: 3
Classifier: Programming Language :: Python :: 3 :: Only
Classifier: Programming Language :: Python :: 3.8
Classifier: Programming Language :: Python :: 3.9
Classifier: License :: OSI Approved :: GNU Lesser General Public License v3 (LGPLv3)
Classifier: Intended Audience :: Developers
Classifier: Operating System :: OS Independent
Requires-Python: >=3.8
License-File: LICENSE
Requires-Dist: pandas ==2.2.2
Requires-Dist: NOBM ==2404.1
Requires-Dist: numpy ==1.23.2
Requires-Dist: OMADS ==2404.1
Requires-Dist: pyyaml
Provides-Extra: interactive
Requires-Dist: matplotlib >=3.5.2 ; extra == 'interactive'
Requires-Dist: plotly >=5.14.1 ; extra == 'interactive'
